papajohnsapi/__init__.py
papajohnsapi_mehtaarn000-0.2.2.dist-info/LICENSE
papajohnsapi_mehtaarn000-0.2.2.dist-info/METADATA
papajohnsapi_mehtaarn000-0.2.2.dist-info/WHEEL
papajohnsapi_mehtaarn000-0.2.2.dist-info/top_level.txt
papajohnsapi_mehtaarn000-0.2.2.dist-info/RECORD
