Metadata-Version: 2.1
Name: papajohnsapi-mehtaarn000
Version: 0.2.2
Summary: A python module that will allow users to use selenium to order pizza from Papa Johns.
Home-page: https://github.com/mehtaarn000/papajohnsapi
Author: mehtaarn000
Author-email: arnavmehta1977@gmail.com
License: UNKNOWN
Platform: UNKNOWN
Classifier: Programming Language :: Python :: 3
Classifier: License :: OSI Approved :: MIT License
Classifier: Operating System :: OS Independent
Requires-Python: >=3.6
